jiojio/__init__.py
jiojio/dataset.py
jiojio/gradient.py
jiojio/inference.py
jiojio/model.py
jiojio/optimizer.py
jiojio/parse_rule_type.py
jiojio/pre_processor.py
jiojio/cws/__init__.py
jiojio/cws/add_dict_to_model.py
jiojio/cws/config.py
jiojio/cws/feature_extractor.py
jiojio/cws/predict_text.py
jiojio/cws/scorer.py
jiojio/cws/tag_words_converter.py
jiojio/cws/trainer.py
jiojio/dictionary/__init__.py
jiojio/dictionary/a.txt
jiojio/dictionary/ad.txt
jiojio/dictionary/an.txt
jiojio/dictionary/c.txt
jiojio/dictionary/d.txt
jiojio/dictionary/f.txt
jiojio/dictionary/m.txt
jiojio/dictionary/n.txt
jiojio/dictionary/nr.txt
jiojio/dictionary/nr1.txt
jiojio/dictionary/nrf.txt
jiojio/dictionary/ns.txt
jiojio/dictionary/nt.txt
jiojio/dictionary/nz.txt
jiojio/dictionary/o.txt
jiojio/dictionary/p.txt
jiojio/dictionary/q.txt
jiojio/dictionary/r.txt
jiojio/dictionary/s.txt
jiojio/dictionary/t.txt
jiojio/dictionary/u.txt
jiojio/dictionary/v.txt
jiojio/dictionary/vi.txt
jiojio/dictionary/w.txt
jiojio/dictionary/wx.txt
jiojio/dictionary/x.txt
jiojio/jiojio_cpp/cwsFeatureExtractor.c
jiojio/jiojio_cpp/cwsFeatureToIndex.c
jiojio/jiojio_cpp/cwsInterface.c
jiojio/jiojio_cpp/cwsPrediction.c
jiojio/jiojio_cpp/posFeatureExtractor.c
jiojio/jiojio_cpp/tagWordsConverter.c
jiojio/jiojio_cpp/wchar_t_hash_dict.c
jiojio/jiojio_cpp/wchar_t_hash_set.c
jiojio/models/__init__.py
jiojio/models/default_cws_model/__init__.py
jiojio/models/default_cws_model/features.json
jiojio/models/default_cws_model/opposite_diff.txt
jiojio/models/default_cws_model/params.json
jiojio/models/default_cws_model/weights.npz
jiojio/models/default_pos_model/__init__.py
jiojio/models/default_pos_model/features.json
jiojio/models/default_pos_model/params.json
jiojio/models/default_pos_model/weights.npz
jiojio/pos/__init__.py
jiojio/pos/add_dict_to_model.py
jiojio/pos/config.py
jiojio/pos/feature_extractor.py
jiojio/pos/pos_types.yml
jiojio/pos/predict_text.py
jiojio/pos/read_default_dict.py
jiojio/pos/trainer.py
jiojio-1.2.8.dist-info/LICENSE
jiojio-1.2.8.dist-info/METADATA
jiojio-1.2.8.dist-info/WHEEL
jiojio-1.2.8.dist-info/top_level.txt
jiojio-1.2.8.dist-info/RECORD
