Metadata-Version: 2.1
Name: jiojio
Version: 1.2.8
Summary: jiojio: a convenient Chinese word segmentation tool
Home-page: https://github.com/dongrixinyu/jiojio
Author: dongrixinyu
Author-email: dongrixinyu.89@163.com
License: UNKNOWN
Platform: UNKNOWN
Classifier: Programming Language :: Python :: 3
Classifier: License :: OSI Approved :: GNU General Public License v3 (GPLv3)
Classifier: Operating System :: OS Independent
Classifier: Topic :: Text Processing
Classifier: Topic :: Scientific/Engineering :: Artificial Intelligence
License-File: LICENSE
Requires-Dist: pyyaml
Requires-Dist: numpy (>=1.16.0)
